zscheduler-0.0.4.dist-info/licenses/LICENSE
zscheduler_app/__init__.py
zscheduler_app/main.py
zscheduler_app/cli/cli.py
zscheduler_app/config/__init__.py
zscheduler_app/config/app_config.py
zscheduler_app/data/__init__.py
zscheduler_app/data/json_store.py
zscheduler_app/scheduler/__init__.py
zscheduler_app/scheduler/scheduler.py
zscheduler_app/themes/__init__.py
zscheduler_app/themes/stylesheet.py
zscheduler_app/themes/theme_manager.py
zscheduler_app/ui/__init__.py
zscheduler_app/ui/about_dialog.py
zscheduler_app/ui/calendar_view.py
zscheduler_app/ui/icons.py
zscheduler_app/ui/main_window.py
zscheduler_app/ui/new_schedule_dialog.py
zscheduler_app/ui/schedule_list_view.py
zscheduler_app/ui/settings_dialog.py
zscheduler_app/ui/statistics_dashboard.py
zscheduler_app/ui/system_tray.py
zscheduler_app/ui/timeline_view.py
zscheduler_lib/README.md
zscheduler_lib/setup.py
zscheduler_lib/zscheduler/__init__.py
zscheduler_lib/zscheduler/core/schedule.py
zscheduler_lib/zscheduler/core/schedule_builder.py
zscheduler_lib/zscheduler/core/scheduler.py
zscheduler_lib/zscheduler/events/event_emitter.py
zscheduler_lib/zscheduler/persistence/json_store.py
zscheduler_lib/zscheduler/tasks/command_task.py
zscheduler_lib/zscheduler/tasks/python_task.py
zscheduler_lib/zscheduler/tasks/task.py
zscheduler_lib/zscheduler/utils/time_parser.py
zscheduler-0.0.4.dist-info/METADATA
zscheduler-0.0.4.dist-info/WHEEL
zscheduler-0.0.4.dist-info/entry_points.txt
zscheduler-0.0.4.dist-info/top_level.txt
zscheduler-0.0.4.dist-info/RECORD
