Metadata-Version: 2.4
Name: zscheduler
Version: 0.0.4
Summary: A simple task scheduling application for commands and python.
Author-email: Yusef Ulum <yusef314159@gmail.com>
License-Expression: MIT
Project-URL: Homepage, https://github.com/mexyusef/zscheduler
Project-URL: Repository, https://github.com/mexyusef/zscheduler
Project-URL: Issues, https://github.com/mexyusef/zscheduler/issues
Keywords: scheduler,task,automation,gui,pyqt
Classifier: Development Status :: 4 - Beta
Classifier: Intended Audience :: End Users/Desktop
Classifier: Programming Language :: Python :: 3
Classifier: Programming Language :: Python :: 3.8
Classifier: Programming Language :: Python :: 3.9
Classifier: Programming Language :: Python :: 3.10
Classifier: Programming Language :: Python :: 3.11
Classifier: Operating System :: Microsoft :: Windows
Classifier: Operating System :: POSIX :: Linux
Classifier: Operating System :: MacOS
Classifier: Environment :: X11 Applications :: Qt
Classifier: Topic :: Utilities
Requires-Python: >=3.8
License-File: LICENSE
Requires-Dist: PyQt6<7.0.0,>=6.4.0
Requires-Dist: pyqtgraph<1.0.0,>=0.13.1
Requires-Dist: python-dateutil>=2.8.2
Requires-Dist: apscheduler<4.0.0,>=3.10.0
Requires-Dist: croniter<7.0.0,>=1.3.0
Requires-Dist: pytz>=2022.1
Dynamic: license-file
